odoo/addons/project_task_description_template_section/README.rst
odoo/addons/project_task_description_template_section/__init__.py
odoo/addons/project_task_description_template_section/__manifest__.py
odoo/addons/project_task_description_template_section/i18n/es.po
odoo/addons/project_task_description_template_section/models/__init__.py
odoo/addons/project_task_description_template_section/models/project_task.py
odoo/addons/project_task_description_template_section/models/project_task_description_template.py
odoo/addons/project_task_description_template_section/readme/CONFIGURE.md
odoo/addons/project_task_description_template_section/readme/CONTRIBUTORS.md
odoo/addons/project_task_description_template_section/readme/DESCRIPTION.md
odoo/addons/project_task_description_template_section/readme/ROADMAP.md
odoo/addons/project_task_description_template_section/readme/USAGE.md
odoo/addons/project_task_description_template_section/static/description/icon.png
odoo/addons/project_task_description_template_section/static/description/index.html
odoo/addons/project_task_description_template_section/tests/__init__.py
odoo/addons/project_task_description_template_section/tests/test_project_task_description_template_section.py
odoo/addons/project_task_description_template_section/views/project_task_description_template_view.xml
odoo_addon_project_task_description_template_section-16.0.1.0.0.2.dist-info/METADATA
odoo_addon_project_task_description_template_section-16.0.1.0.0.2.dist-info/WHEEL
odoo_addon_project_task_description_template_section-16.0.1.0.0.2.dist-info/top_level.txt
odoo_addon_project_task_description_template_section-16.0.1.0.0.2.dist-info/RECORD
