Metadata-Version: 2.1
Name: odoo-addon-project_task_description_template_section
Version: 16.0.1.0.0.2
Requires-Python: >=3.10
Requires-Dist: odoo-addon-project_task_description_template>=16.0dev,<16.1dev
Requires-Dist: odoo>=16.0a,<16.1dev
Summary: Project Task Description Template Section
Home-page: https://github.com/sygel-technology/sy-project
License: AGPL-3
Author: Sygel, Odoo Community Association (OCA)
Author-email: support@odoo-community.org
Classifier: Programming Language :: Python
Classifier: Framework :: Odoo
Classifier: Framework :: Odoo :: 16.0
Classifier: License :: OSI Approved :: GNU Affero General Public License v3
